Workbook

Sheet Casos
A1: ID | B1: Módulo | C1: Prioridad | D1: Caso | E1: Pasos | F1: Resultado esperado | G1: Resultado obtenido | H1: Estado | I1: Observaciones / defecto | J1: Probado por | K1: Fecha
A2: CP-SEG-01 | B2: Seguridad / Autenticación | C2: Alta | D2: Registro exitoso | E2: Registrar con datos válidos + aceptar términos
A3: CP-SEG-02 | B3: Seguridad / Autenticación | C3: Media | D3: Registro email duplicado | E3: Registrar con un email ya existente
A4: CP-SEG-03 | B4: Seguridad / Autenticación | C4: Media | D4: Registro teléfono/datos inválidos | E4: Teléfono no numérico / NIT vacío
A5: CP-SEG-04 | B5: Seguridad / Autenticación | C5: Alta | D5: Activación de cuenta | E5: Abrir el enlace de activación del correo
A6: CP-SEG-05 | B6: Seguridad / Autenticación | C6: Baja | D6: Activación con clave vencida/errada | E6: Usar un qs inválido
A7: CP-SEG-06 | B7: Seguridad / Autenticación | C7: Alta | D7: Login exitoso | E7: Login con credenciales correctas de cuenta activa
A8: CP-SEG-07 | B8: Seguridad / Autenticación | C8: Alta | D8: Login contraseña incorrecta | E8: Contraseña errada
A9: CP-SEG-08 | B9: Seguridad / Autenticación | C9: Media | D9: Login usuario inexistente | E9: Email que no existe
A10: CP-SEG-09 | B10: Seguridad / Autenticación | C10: Media | D10: Login cuenta inactiva | E10: Cuenta sin activar
A11: CP-SEG-10 | B11: Seguridad / Autenticación | C11: Alta | D11: Auditoría de seguridad — ingreso | E11: Login exitoso → revisar tab Auditoría
A12: CP-SEG-11 | B12: Seguridad / Autenticación | C12: Media | D12: Auditoría — contraseña incorrecta | E12: Login con clave errada → Auditoría
A13: CP-SEG-12 | B13: Seguridad / Autenticación | C13: Media | D13: Auditoría — usuario inexistente | E13: Login con email inexistente → Auditoría
... A423: CP-REG-05 | B423: Regresión / transversales | C423: Baja | D423: Responsive | E423: Portal/admin en móvil

Sheet Resumen
A1: Resumen de ejecución — Casos de prueba QA MailConnect
A2: Se calcula solo desde la hoja "Casos". No escribir aquí.
A4: Total de casos | B4: =COUNTA(Casos!A2:A423)
A5: Pasó | B5: =COUNTIF(Casos!$H$2:$H$423,A5) | C5: =IFERROR(B5/$B$4,0)
A6: No pasó | B6: =COUNTIF(Casos!$H$2:$H$423,A6) | C6: =IFERROR(B6/$B$4,0)
A7: Bloqueado | B7: =COUNTIF(Casos!$H$2:$H$423,A7) | C7: =IFERROR(B7/$B$4,0)
A8: No aplica | B8: =COUNTIF(Casos!$H$2:$H$423,A8) | C8: =IFERROR(B8/$B$4,0)
A9: Sin ejecutar | B9: =$B$4-SUM(B5:B8) | C9: =IFERROR(B9/$B$4,0)
A11: Por prioridad | C11: Con fallo
A12: Alta | B12: =COUNTIF(Casos!$C$2:$C$423,A12) | C12: =COUNTIFS(Casos!$C$2:$C$423,A12,Casos!$H$2:$H$423,"No pasó")
A13: Media | B13: =COUNTIF(Casos!$C$2:$C$423,A13) | C13: =COUNTIFS(Casos!$C$2:$C$423,A13,Casos!$H$2:$H$423,"No pasó")
A14: Baja | B14: =COUNTIF(Casos!$C$2:$C$423,A14) | C14: =COUNTIFS(Casos!$C$2:$C$423,A14,Casos!$H$2:$H$423,"No pasó")
A16: Por módulo
A17: Módulo | B17: Casos | C17: Pasó | D17: No pasó | E17: Sin ejecutar
A18: Seguridad / Autenticación | B18: =COUNTIF(Casos!$B$2:$B$423,$A18) | C18: =COUNTIFS(Casos!$B$2:$B$423,$A18,Casos!$H$2:$H$423,"Pasó") | D18: =COUNTIFS(Casos!$B$2:$B$423,$A18,Casos!$H$2:$H$423,"No pasó") | E18: =B18-COUNTIFS(Casos!$B$2:$B$423,$A18,Casos!$H$2:$H$423,"<>")
A19: Auditoría (admin) | B19: =COUNTIF(Casos!$B$2:$B$423,$A19) | C19: =COUNTIFS(Casos!$B$2:$B$423,$A19,Casos!$H$2:$H$423,"Pasó") | D19: =COUNTIFS(Casos!$B$2:$B$423,$A19,Casos!$H$2:$H$423,"No pasó") | E19: =B19-COUNTIFS(Casos!$B$2:$B$423,$A19,Casos!$H$2:$H$423,"<>")
A20: Panel admin | B20: =COUNTIF(Casos!$B$2:$B$423,$A20) | C20: =COUNTIFS(Casos!$B$2:$B$423,$A20,Casos!$H$2:$H$423,"Pasó") | D20: =COUNTIFS(Casos!$B$2:$B$423,$A20,Casos!$H$2:$H$423,"No pasó") | E20: =B20-COUNTIFS(Casos!$B$2:$B$423,$A20,Casos!$H$2:$H$423,"<>")
A21: Portal cliente — Plantillas y Campañas | B21: =COUNTIF(Casos!$B$2:$B$423,$A21) | C21: =COUNTIFS(Casos!$B$2:$B$423,$A21,Casos!$H$2:$H$423,"Pasó") | D21: =COUNTIFS(Casos!$B$2:$B$423,$A21,Casos!$H$2:$H$423,"No pasó") | E21: =B21-COUNTIFS(Casos!$B$2:$B$423,$A21,Casos!$H$2:$H$423,"<>")
A22: Portal cliente — Bases de datos (CSV + Excel) | B22: =COUNTIF(Casos!$B$2:$B$423,$A22) | C22: =COUNTIFS(Casos!$B$2:$B$423,$A22,Casos!$H$2:$H$423,"Pasó") | D22: =COUNTIFS(Casos!$B$2:$B$423,$A22,Casos!$H$2:$H$423,"No pasó") | E22: =B22-COUNTIFS(Casos!$B$2:$B$423,$A22,Casos!$H$2:$H$423,"<>")
A23: Portal cliente — Muestras, Envío real, Reportes, Estadísticas | B23: =COUNTIF(Casos!$B$2:$B$423,$A23) | C23: =COUNTIFS(Casos!$B$2:$B$423,$A23,Casos!$H$2:$H$423,"Pasó") | D23: =COUNTIFS(Casos!$B$2:$B$423,$A23,Casos!$H$2:$H$423,"No pasó") | E23: =B23-COUNTIFS(Casos!$B$2:$B$423,$A23,Casos!$H$2:$H$423,"<>")
A24: Envíos multicanal + estados de entrega | B24: =COUNTIF(Casos!$B$2:$B$423,$A24) | C24: =COUNTIFS(Casos!$B$2:$B$423,$A24,Casos!$H$2:$H$423,"Pasó") | D24: =COUNTIFS(Casos!$B$2:$B$423,$A24,Casos!$H$2:$H$423,"No pasó") | E24: =B24-COUNTIFS(Casos!$B$2:$B$423,$A24,Casos!$H$2:$H$423,"<>")
A25: Trabajos — Reintentar / Reencolar | B25: =COUNTIF(Casos!$B$2:$B$423,$A25) | C25: =COUNTIFS(Casos!$B$2:$B$423,$A25,Casos!$H$2:$H$423,"Pasó") | D25: =COUNTIFS(Casos!$B$2:$B$423,$A25,Casos!$H$2:$H$423,"No pasó") | E25: =B25-COUNTIFS(Casos!$B$2:$B$423,$A25,Casos!$H$2:$H$423,"<>")
A26: Rendimiento / escalabilidad (verificación técnica) | B26: =COUNTIF(Casos!$B$2:$B$423,$A26) | C26: =COUNTIFS(Casos!$B$2:$B$423,$A26,Casos!$H$2:$H$423,"Pasó") | D26: =COUNTIFS(Casos!$B$2:$B$423,$A26,Casos!$H$2:$H$423,"No pasó") | E26: =B26-COUNTIFS(Casos!$B$2:$B$423,$A26,Casos!$H$2:$H$423,"<>")
A27: Portal de pagos — Prepago (implementado; ver la sección Prepago en CLAUDE.md) | B27: =COUNTIF(Casos!$B$2:$B$423,$A27) | C27: =COUNTIFS(Casos!$B$2:$B$423,$A27,Casos!$H$2:$H$423,"Pasó") | D27: =COUNTIFS(Casos!$B$2:$B$423,$A27,Casos!$H$2:$H$423,"No pasó") | E27: =B27-COUNTIFS(Casos!$B$2:$B$423,$A27,Casos!$H$2:$H$423,"<>")
A28: Constructor de correos HTML | B28: =COUNTIF(Casos!$B$2:$B$423,$A28) | C28: =COUNTIFS(Casos!$B$2:$B$423,$A28,Casos!$H$2:$H$423,"Pasó") | D28: =COUNTIFS(Casos!$B$2:$B$423,$A28,Casos!$H$2:$H$423,"No pasó") | E28: =B28-COUNTIFS(Casos!$B$2:$B$423,$A28,Casos!$H$2:$H$423,"<>")
A29: Plantillas PDF (básicas · Estudio · Diseñador) | B29: =COUNTIF(Casos!$B$2:$B$423,$A29) | C29: =COUNTIFS(Casos!$B$2:$B$423,$A29,Casos!$H$2:$H$423,"Pasó") | D29: =COUNTIFS(Casos!$B$2:$B$423,$A29,Casos!$H$2:$H$423,"No pasó") | E29: =B29-COUNTIFS(Casos!$B$2:$B$423,$A29,Casos!$H$2:$H$423,"<>")
... A39: Regresión / transversales | B39: =COUNTIF(Casos!$B$2:$B$423,$A39) | C39: =COUNTIFS(Casos!$B$2:$B$423,$A39,Casos!$H$2:$H$423,"Pasó") | D39: =COUNTIFS(Casos!$B$2:$B$423,$A39,Casos!$H$2:$H$423,"No pasó") | E39: =B39-COUNTIFS(Casos!$B$2:$B$423,$A39,Casos!$H$2:$H$423,"<>")

Sheet Cómo usarla
A1: Cómo usar esta planilla
A3: 1. Ejecuta los casos de la hoja "Casos" en orden o filtrando por módulo/prioridad.
A4: 2. Llena SOLO las columnas amarillas: Resultado obtenido, Estado, Observaciones,
A5: Probado por y Fecha. Las demás vienen del documento y no se editan aquí.
A6: 3. "Estado" es un desplegable: Pasó / No pasó / Bloqueado / No aplica.
A7: Usa "Bloqueado" cuando el caso no se pudo ejecutar por una dependencia
A8: (por ejemplo, un endpoint que todavía no está desplegado — ver DESPLIEGUE.md).
A9: 4. La hoja "Resumen" se calcula sola a partir de la columna Estado. Si al abrir
A10: el archivo el resumen sale en blanco, pulsa F9 (recalcular): las fórmulas se
A11: escriben sin valores cacheados y Excel las evalúa al abrir.
A13: Ojo: esta planilla se GENERA desde CASOS_PRUEBA_QA.md.
A14: Si se agregan casos al documento y se vuelve a generar, lo que hayas escrito aquí
... A18: Prioridades: Alta = crítico (bloquea salida a producción) · Media · Baja.
